<library path="lib/libexotica_ompl_solver">
  <class name="exotica/RRTSolver" type="exotica::RRTSolver" base_class_type="exotica::MotionSolver">
    <description>RRTSolver</description>
  </class>
  <class name="exotica/RRTConnectSolver" type="exotica::RRTConnectSolver" base_class_type="exotica::MotionSolver">
    <description>RRTConnectSolver</description>
  </class>
  <class name="exotica/ESTSolver" type="exotica::ESTSolver" base_class_type="exotica::MotionSolver">
    <description>RRT</description>
  </class>
  <class name="exotica/KPIECESolver" type="exotica::KPIECESolver" base_class_type="exotica::MotionSolver">
    <description>RRT</description>
  </class>
  <class name="exotica/BKPIECESolver" type="exotica::BKPIECESolver" base_class_type="exotica::MotionSolver">
    <description>RRT</description>
  </class>
  <class name="exotica/PRMSolver" type="exotica::PRMSolver" base_class_type="exotica::MotionSolver">
    <description>Probabilistic Roadmap</description>
  </class>
  <class name="exotica/LazyPRMSolver" type="exotica::LazyPRMSolver" base_class_type="exotica::MotionSolver">
    <description>Probabilistic Roadmap</description>
  </class>
  <class name="exotica/RRTStarSolver" type="exotica::RRTStarSolver" base_class_type="exotica::MotionSolver">
    <description>RRTStarSolver</description>
  </class>
  <class name="exotica/LBTRRTSolver" type="exotica::LBTRRTSolver" base_class_type="exotica::MotionSolver">
    <description>LBTRRTSolver</description>
  </class>
</library>
