<?xml version="1.0" ?>
<DynamicTimeIndexedProblemConfig>
    <!-- <ILQRSolver Name="ILQRSolver">
        <Debug>1</Debug>
        <MaxIterations>50</MaxIterations>
        <FunctionTolerance>-1</FunctionTolerance>
        <FunctionTolerancePatience>50</FunctionTolerancePatience>
    </ILQRSolver> -->
    <!-- <ILQGSolver Name="ILQRSolver">
        <Debug>1</Debug>
        <MaxIterations>50</MaxIterations>
        <FunctionTolerance>-1</FunctionTolerance>
        <FunctionTolerancePatience>50</FunctionTolerancePatience>
    </ILQGSolver> -->

    <!-- <ControlLimitedDDPSolver Name="ControlLimitedDDPSolver">
        <Debug>1</Debug>
        <MaxIterations>200</MaxIterations>
        <FunctionTolerance>-1</FunctionTolerance>
        <FunctionTolerancePatience>200</FunctionTolerancePatience>
        <UseSecondOrderDynamics>0</UseSecondOrderDynamics>
        <ConditioningRate>3</ConditioningRate>
    </ControlLimitedDDPSolver> -->
    <AnalyticDDPSolver Name="ControlLimitedDDPSolver">
        <Debug>1</Debug>
        <MaxIterations>200</MaxIterations>
        <FunctionTolerance>-1</FunctionTolerance>
        <FunctionTolerancePatience>200</FunctionTolerancePatience>
        <UseSecondOrderDynamics>0</UseSecondOrderDynamics>
        <LambdaMax>1e5</LambdaMax>
        <ConditioningRate>1e-5</ConditioningRate>
    </AnalyticDDPSolver>
    
    <DynamicTimeIndexedShootingProblem Name="MyProblem">
        <PlanningScene>
            <Scene>
                <JointGroup>arm</JointGroup>
                <URDF>{exotica_examples}/resources/robots/lwr_simplified.urdf</URDF>
                <SRDF>{exotica_examples}/resources/robots/lwr_simplified.srdf</SRDF>
                <SetRobotDescriptionRosParams>1</SetRobotDescriptionRosParams>

                <DynamicsSolver>
                    <DoubleIntegratorDynamicsSolver Name="solver" Integrator="RK1">
                        <ControlLimits>5</ControlLimits>
                        <dt>0.01</dt>
                    </DoubleIntegratorDynamicsSolver>
                    <!-- <PinocchioDynamicsSolver Name="solver" Integrator="RK1">
                        <ControlLimits>156</ControlLimits>
                        <dt>0.01</dt>
                    </PinocchioDynamicsSolver> -->
                </DynamicsSolver>
            </Scene>
        </PlanningScene>

        <Maps>
            <EffPosition Name="Position">
                <EndEffector>
                    <Frame Link="lwr_arm_6_link" LinkOffset="0 0 0 0.7071067811865476 -4.3297802811774664e-17  0.7071067811865475 4.3297802811774664e-17"/>
                </EndEffector>
            </EffPosition>
            <JointLimit Name="JL"/>
        </Maps>

        <Cost>
            <!-- <Task Task="JL" Rho="0.01"/> -->

            <Task Task="Position" Goal="0.0 0.5 0.5" Rho="0 0 0 0 0 0 0 0 0 0 0 0 0 0 0 0 0 0 0 0 0 0 0 0 0 0 0 0 0 0 0 0 0 0 0 0 0 0 0 0 0 0 0 0 0 0 0 0 0 0 0 0 0 0 0 0 0 0 0 0 0 0 0 0 0 0 0 0 0 0 0 0 0 0 0 0 0 0 0 0 0 0 0 0 0 0 0 0 0 0 0 0 0 0 0 0 0 0 0 0 0 0 0 0 0 0 0 0 0 0 0 0 0 0 0 0 0 0 0 0 0 0 0 0 0 0 0 0 0 0 0 0 0 0 0 0 0 0 0 0 0 0 0 0 0 0 0 0 0 100.0"/>
            <!-- <Task Task="Position" Goal="0 0.5 0.5" Rho="0 0 0 0 0 0 0 0 0 0 0 0 0 0 0 0 0 0 0 0 0 0 0 0 0 0 0 0 0 0 0 0 0 0 0 0 0 0 0 0 0 0 0 0 0 0 0 0 0 0 0 0 0 0 0 0 0 0 0 0 0 0 0 0 0 0 0 0 0 0 0 0 0 0 0 0 0 0 0 0 0 0 0 0 0 0 0 0 0 0 0 0 0 0 0 0 0 0 0.0 0 0 0 0 0 0 0 0 0 0 0 0 0 0 0 0 0 0 0 0 0 0 0 0 0 0 0 0 0 0 0 0 0 0 0 0 0 0 0 0 0 0 0 0 0 0 0 0 0 0 0 0 0 0 0 0 0 0 0 0 0 0 0 0 0 0 0 0 0 0 0 0 0 0 0 0 0 0 0 0 0 0 0 0 0 0 0 0 0 0 0 0 0 0 0 0 0 0 0 0.0 100.0"/> -->
        </Cost>
        
        <T>150</T>
        <tau>0.01</tau>
        <dt>0.01</dt>
        <Q>0 0 0 0 0 0 0 1 1 1 1 1 1 1</Q>
        <Q_rate>0.01</Q_rate>
        <Qf>0 0 0 0 0 0 0 1 1 1 1 1 1 1</Qf>
        <Qf_rate>100</Qf_rate>

        <R_rate>0.01</R_rate>
        <StartState>0 0 0  0 0 0 0 0 0 0 0 0 0 0</StartState>
        <GoalState> 0 0 0  0 0 0 0 0 0 0 0 0 0 0</GoalState>
        <!-- <StartState>0 0 0 -1.35 0 0 0 0 0 0 0 0 0 0</StartState>
        <GoalState> 0 0 0  0 0 0 0 0 0 0 0 0 0 0</GoalState> -->

        <WarmStartWithInverseDynamics>0</WarmStartWithInverseDynamics>
    </DynamicTimeIndexedShootingProblem>
</DynamicTimeIndexedProblemConfig>
